partridge/__init__.py
partridge/__version__.py
partridge/config.py
partridge/geo.py
partridge/gtfs.py
partridge/parsers.py
partridge/readers.py
partridge/types.py
partridge/utilities.py
partridge/writers.py
partridge-1.1.2.dist-info/LICENSE
partridge-1.1.2.dist-info/METADATA
partridge-1.1.2.dist-info/WHEEL
partridge-1.1.2.dist-info/top_level.txt
partridge-1.1.2.dist-info/RECORD
