Metadata-Version: 2.1
Name: partridge
Version: 1.1.2
Summary: Partridge is a python library for working with GTFS feeds using pandas DataFrames.
Home-page: https://github.com/remix/partridge
Author: Danny Whalen
Author-email: daniel.r.whalen@gmail.com
License: MIT license
Keywords: partridge
Classifier: Intended Audience :: Developers
Classifier: License :: OSI Approved :: MIT License
Classifier: Natural Language :: English
Classifier: Programming Language :: Python :: 3
Classifier: Programming Language :: Python :: 3.6
Classifier: Programming Language :: Python :: 3.7
Requires-Python: >=3.6, <4
License-File: LICENSE
Requires-Dist: charset-normalizer
Requires-Dist: networkx >=2.0
Requires-Dist: pandas
Requires-Dist: isoweek
Requires-Dist: functools32 ; python_version < "3"
Provides-Extra: full
Requires-Dist: geopandas ; extra == 'full'
